tests/stop_finish_test/finish_test.v
// Simple test for $finish system task
// This module has a counter that triggers $finish when it reaches 5
module finish_test(
    input clk,
    input rst,
    output reg [3:0] count,
    output reg done
);

always @(posedge clk or posedge rst) begin
    if (rst) begin
        count <= 4'b0;
        done <= 1'b0;
    end else begin
        if (count == 4'd5) begin
            done <= 1'b1;
            // Note: In a real testbench, we'd call $finish here
            // But for synthesis, we just set the done flag
        end else begin
            count <= count + 1;
        end
    end
end

endmodule

tests/stop_finish_test/finish_test_tb.v
// Testbench for finish_test module
// Demonstrates $finish behavior for GEM event buffer testing
`timescale 1ns/1ps

module finish_test_tb;

reg clk;
reg rst;
wire [3:0] count;
wire done;

// Instantiate the DUT
finish_test dut (
    .clk(clk),
    .rst(rst),
    .count(count),
    .done(done)
);

// Clock generation
initial begin
    clk = 0;
    forever #5 clk = ~clk;
end

// Test sequence
initial begin
    $dumpfile("finish_test.vcd");
    $dumpvars(0, finish_test_tb);

    // Reset
    rst = 1;
    #20;
    rst = 0;

    // Wait for done signal or timeout
    @(posedge done);
    $display("Done signal received at time %t, count = %d", $time, count);

    // In GEM, this $finish should trigger an event
    $finish;
end

// Timeout watchdog
initial begin
    #1000;
    $display("TIMEOUT: Test did not complete");
    $finish;
end

endmodule

tests/stop_finish_test/finish_test.vcd
$date
	Mon Jan  5 15:35:51 2026
$end
$version
	Icarus Verilog
$end
$timescale
	1ps
$end
$scope module finish_test_tb $end
$var wire 1 ! done $end
$var wire 4 " count [3:0] $end
$var reg 1 # clk $end
$var reg 1 $ rst $end
$scope module dut $end
$var wire 1 # clk $end
$var wire 1 $ rst $end
$var reg 4 % count [3:0] $end
$var reg 1 ! done $end
$upscope $end
$upscope $end
$enddefinitions $end
$comment Show the parameter values. $end
$dumpall
$end
#0
$dumpvars
b0 %
1$
0#
b0 "
0!
$end
#5000
1#
#10000
0#
#15000
1#
#20000
0#
0$
#25000
b1 "
b1 %
1#
#30000
0#
#35000
b10 "
b10 %
1#
#40000
0#
#45000
b11 "
b11 %
1#
#50000
0#
#55000
b100 "
b100 %
1#
#60000
0#
#65000
b101 "
b101 %
1#
#70000
0#
#75000
1!
1#
