tests/assert_test/assert_simple.v
// Simple assertion test for GEM
// Uses immediate assertions which synthesize to $assert/$check cells

module assert_simple (
    input wire clk,
    input wire rst,
    input wire [3:0] data_in,
    output reg [3:0] data_out,
    output reg overflow_flag
);

// Simple counter to generate test conditions
reg [3:0] counter;

always @(posedge clk) begin
    if (rst) begin
        counter <= 4'd0;
        data_out <= 4'd0;
        overflow_flag <= 1'b0;
    end else begin
        counter <= counter + 1'b1;
        data_out <= data_in;

        // Track overflow condition
        if (data_in == 4'hF && counter > 4'd10) begin
            overflow_flag <= 1'b1;
        end
    end
end

// Wire for assertion condition
wire no_overflow_condition = !(data_in == 4'hF && counter > 4'd10) || rst;

// For formal verification - this should create an $assert cell
// We'll use the (* keep *) attribute to prevent optimization

`ifdef FORMAL
always @(posedge clk) begin
    // Assertion: no overflow when reset is active
    assert(rst || !(data_in == 4'hF && counter > 4'd10));
end
`endif

endmodule

tests/assert_test/assert_tb.v
// Testbench for assert_simple module
`timescale 1ns/1ps

module assert_tb;

reg clk;
reg rst;
reg [3:0] data_in;
wire [3:0] data_out;
wire overflow_flag;

// Instantiate the DUT
assert_simple dut (
    .clk(clk),
    .rst(rst),
    .data_in(data_in),
    .data_out(data_out),
    .overflow_flag(overflow_flag)
);

// Clock generation
initial begin
    clk = 0;
    forever #5 clk = ~clk;
end

// Test sequence
initial begin
    $dumpfile("assert_test.vcd");
    $dumpvars(0, assert_tb);

    // Initialize
    rst = 1;
    data_in = 4'h0;
    #20;
    rst = 0;

    // Normal operation - counter runs from 0 to 15
    // At cycle 11+ (counter > 10), if data_in == 0xF, assertion should fail

    // Run for a while with safe data
    repeat(10) begin
        data_in = $random % 14;  // 0-13, never 15
        #10;
    end

    // Now trigger assertion failure: counter > 10 and data_in = 0xF
    data_in = 4'hF;  // This should trigger assertion at cycle 11+
    #10;

    // Continue with more cycles
    data_in = 4'h5;
    #50;

    $display("Test completed");
    $finish;
end

endmodule

tests/assert_test/assert_test.vcd
$date
	Tue Jan  6 21:01:23 2026
$end
$version
	Icarus Verilog
$end
$timescale
	1ps
$end
$scope module assert_tb $end
$var wire 1 ! overflow_flag $end
$var wire 4 " data_out [3:0] $end
$var reg 1 # clk $end
$var reg 4 $ data_in [3:0] $end
$var reg 1 % rst $end
$scope module dut $end
$var wire 1 # clk $end
$var wire 4 & data_in [3:0] $end
$var wire 1 ' no_overflow_condition $end
$var wire 1 % rst $end
$var reg 4 ( counter [3:0] $end
$var reg 4 ) data_out [3:0] $end
$var reg 1 ! overflow_flag $end
$upscope $end
$upscope $end
$enddefinitions $end
$comment Show the parameter values. $end
$dumpall
$end
#0
$dumpvars
bx )
bx (
1'
b0 &
1%
b0 $
0#
bx "
x!
$end
#5000
0!
b0 "
b0 )
b0 (
1#
#10000
0#
#15000
1#
#20000
0#
0%
#25000
b1 (
1#
#30000
0#
b11 $
b11 &
#35000
b11 "
b11 )
b10 (
1#
#40000
0#
b1101 $
b1101 &
#45000
b1101 "
b1101 )
b11 (
1#
#50000
0#
#55000
b100 (
1#
#60000
0#
#65000
b101 (
1#
#70000
0#
b1001 $
b1001 &
#75000
b1001 "
b1001 )
b110 (
1#
#80000
0#
b11 $
b11 &
#85000
b11 "
b11 )
b111 (
1#
#90000
0#
b1010 $
b1010 &
#95000
b1010 "
b1010 )
b1000 (
1#
#100000
0#
b1001 $
b1001 &
#105000
b1001 "
b1001 )
b1001 (
1#
#110000
0#
#115000
b1010 (
1#
#120000
0#
b1111 $
b1111 &
#125000
0'
b1111 "
b1111 )
b1011 (
1#
#130000
1'
0#
b101 $
b101 &
#135000
b101 "
b101 )
b1100 (
1#
#140000
0#
#145000
b1101 (
1#
#150000
0#
#155000
b1110 (
1#
#160000
0#
#165000
b1111 (
1#
#170000
0#
#175000
b0 (
1#
